modern_python_sample/__init__.py
modern_python_sample/console.py
modern_python_sample-0.0.1.dist-info/LICENSE
modern_python_sample-0.0.1.dist-info/METADATA
modern_python_sample-0.0.1.dist-info/WHEEL
modern_python_sample-0.0.1.dist-info/entry_points.txt
modern_python_sample-0.0.1.dist-info/RECORD
